{"product":{"id":7940456054983,"title":"Commission for Muneera: Moon Ducks and Engaged Ducks","body_html":"\u003cp\u003eThis is a set of 2 glass figurines of ducks for Muneera- expecting ducks on the moon with a house and egg \u0026amp; engaged ducks with tie and \"diamond\" ring. : )\u003cbr\u003e\u003c\/p\u003e\n\u003cp\u003eDimensions: Moon ducks sculpture approximately 3 inches wide x 2 inches deep x  2 inches tall\u003cbr\u003eEngaged ducks sculpture approximately 2.5 inches wide x 1.5 inches deep x 1.5 inches tall\u003cbr\u003eMedium: Glass (fragile- do not drop)\u003cbr\u003eYear: 2024\u003c\/p\u003e\n\u003cp\u003e---------------\u003c\/p\u003e\n\u003cp\u003e\u003cem\u003eNote: colors in real life may differ slightly from those in this image.\u003c\/em\u003e\u003cbr\u003e\u003cem\u003eWarning: Small parts- do not ingest- choking hazard.\u003c\/em\u003e\u003c\/p\u003e","vendor":"Jackie Loven Art","product_type":"glass","created_at":"2024-03-18T14:40:47-07:00","handle":"commission-for-muneera-moon-engaged","updated_at":"2026-04-12T17:10:28-07:00","published_at":"2024-04-09T17:05:17-07:00","template_suffix":"","published_scope":"web","tags":"","variants":[{"id":43867192754375,"product_id":7940456054983,"title":"Default Title","price":"480.00","sku":null,"position":1,"compare_at_price":"","fulfillment_service":"manual","inventory_management":"shopify","option1":"Default Title","option2":null,"option3":null,"created_at":"2024-03-18T14:40:47-07:00","updated_at":"2026-04-12T17:10:28-07:00","taxable":true,"barcode":null,"grams":454,"image_id":null,"weight":1.0,"weight_unit":"lb","requires_shipping":true,"quantity_rule":{"min":1,"max":null,"increment":1},"price_currency":"USD","compare_at_price_currency":"","quantity_price_breaks":[]}],"options":[{"id":10100077166791,"product_id":7940456054983,"name":"Title","position":1,"values":["Default Title"]}],"images":[{"id":39195774320839,"product_id":7940456054983,"position":1,"created_at":"2024-04-09T16:56:45-07:00","updated_at":"2024-04-09T16:57:56-07:00","alt":null,"width":2657,"height":2657,"src":"https:\/\/cdn.shopify.com\/s\/files\/1\/0605\/8790\/1127\/files\/IMG_1474.heic?v=1712707076","variant_ids":[]},{"id":39195773370567,"product_id":7940456054983,"position":2,"created_at":"2024-04-09T16:56:45-07:00","updated_at":"2024-04-09T16:57:56-07:00","alt":null,"width":1080,"height":1080,"src":"https:\/\/cdn.shopify.com\/s\/files\/1\/0605\/8790\/1127\/files\/4.png?v=1712707076","variant_ids":[]},{"id":39195773468871,"product_id":7940456054983,"position":3,"created_at":"2024-04-09T16:56:45-07:00","updated_at":"2024-04-09T16:57:56-07:00","alt":null,"width":1080,"height":1080,"src":"https:\/\/cdn.shopify.com\/s\/files\/1\/0605\/8790\/1127\/files\/5.png?v=1712707076","variant_ids":[]},{"id":39195773239495,"product_id":7940456054983,"position":4,"created_at":"2024-04-09T16:56:45-07:00","updated_at":"2024-04-09T16:57:56-07:00","alt":null,"width":1934,"height":1934,"src":"https:\/\/cdn.shopify.com\/s\/files\/1\/0605\/8790\/1127\/files\/IMG_1441.heic?v=1712707076","variant_ids":[]},{"id":39195773272263,"product_id":7940456054983,"position":5,"created_at":"2024-04-09T16:56:45-07:00","updated_at":"2024-04-09T16:57:56-07:00","alt":null,"width":2004,"height":2004,"src":"https:\/\/cdn.shopify.com\/s\/files\/1\/0605\/8790\/1127\/files\/IMG_1444.heic?v=1712707076","variant_ids":[]},{"id":39195774156999,"product_id":7940456054983,"position":6,"created_at":"2024-04-09T16:56:45-07:00","updated_at":"2024-04-09T16:57:56-07:00","alt":null,"width":1080,"height":1080,"src":"https:\/\/cdn.shopify.com\/s\/files\/1\/0605\/8790\/1127\/files\/1.png?v=1712707076","variant_ids":[]},{"id":39195773665479,"product_id":7940456054983,"position":7,"created_at":"2024-04-09T16:56:45-07:00","updated_at":"2024-04-09T16:57:56-07:00","alt":null,"width":2254,"height":2254,"src":"https:\/\/cdn.shopify.com\/s\/files\/1\/0605\/8790\/1127\/files\/IMG_1455.heic?v=1712707076","variant_ids":[]},{"id":39195774222535,"product_id":7940456054983,"position":8,"created_at":"2024-04-09T16:56:45-07:00","updated_at":"2024-04-09T16:57:56-07:00","alt":null,"width":1886,"height":1886,"src":"https:\/\/cdn.shopify.com\/s\/files\/1\/0605\/8790\/1127\/files\/IMG_1458.heic?v=1712707076","variant_ids":[]},{"id":39195773501639,"product_id":7940456054983,"position":9,"created_at":"2024-04-09T16:56:45-07:00","updated_at":"2024-04-09T16:57:56-07:00","alt":null,"width":2227,"height":2227,"src":"https:\/\/cdn.shopify.com\/s\/files\/1\/0605\/8790\/1127\/files\/IMG_1436.heic?v=1712707076","variant_ids":[]},{"id":39195773993159,"product_id":7940456054983,"position":10,"created_at":"2024-04-09T16:56:45-07:00","updated_at":"2024-04-09T16:57:56-07:00","alt":null,"width":2300,"height":2300,"src":"https:\/\/cdn.shopify.com\/s\/files\/1\/0605\/8790\/1127\/files\/IMG_1440.heic?v=1712707076","variant_ids":[]},{"id":39195773534407,"product_id":7940456054983,"position":11,"created_at":"2024-04-09T16:56:45-07:00","updated_at":"2024-04-09T16:57:56-07:00","alt":null,"width":1951,"height":1951,"src":"https:\/\/cdn.shopify.com\/s\/files\/1\/0605\/8790\/1127\/files\/IMG_1445.heic?v=1712707076","variant_ids":[]},{"id":39195774386375,"product_id":7940456054983,"position":12,"created_at":"2024-04-09T16:56:45-07:00","updated_at":"2024-04-09T16:57:56-07:00","alt":null,"width":2180,"height":2180,"src":"https:\/\/cdn.shopify.com\/s\/files\/1\/0605\/8790\/1127\/files\/IMG_1446.heic?v=1712707076","variant_ids":[]},{"id":39195773403335,"product_id":7940456054983,"position":13,"created_at":"2024-04-09T16:56:45-07:00","updated_at":"2024-04-09T16:57:56-07:00","alt":null,"width":2057,"height":2057,"src":"https:\/\/cdn.shopify.com\/s\/files\/1\/0605\/8790\/1127\/files\/IMG_1447.heic?v=1712707076","variant_ids":[]},{"id":39195773436103,"product_id":7940456054983,"position":14,"created_at":"2024-04-09T16:56:45-07:00","updated_at":"2024-04-09T16:57:56-07:00","alt":null,"width":2036,"height":2036,"src":"https:\/\/cdn.shopify.com\/s\/files\/1\/0605\/8790\/1127\/files\/IMG_1448.heic?v=1712707076","variant_ids":[]},{"id":39195774419143,"product_id":7940456054983,"position":15,"created_at":"2024-04-09T16:56:45-07:00","updated_at":"2024-04-09T16:57:56-07:00","alt":null,"width":2028,"height":2028,"src":"https:\/\/cdn.shopify.com\/s\/files\/1\/0605\/8790\/1127\/files\/IMG_1449.heic?v=1712707076","variant_ids":[]},{"id":39195773305031,"product_id":7940456054983,"position":16,"created_at":"2024-04-09T16:56:45-07:00","updated_at":"2024-04-09T16:57:56-07:00","alt":null,"width":1080,"height":1080,"src":"https:\/\/cdn.shopify.com\/s\/files\/1\/0605\/8790\/1127\/files\/2.png?v=1712707076","variant_ids":[]},{"id":39195773599943,"product_id":7940456054983,"position":17,"created_at":"2024-04-09T16:56:45-07:00","updated_at":"2024-04-09T16:57:56-07:00","alt":null,"width":1080,"height":1080,"src":"https:\/\/cdn.shopify.com\/s\/files\/1\/0605\/8790\/1127\/files\/3.png?v=1712707076","variant_ids":[]},{"id":39195774058695,"product_id":7940456054983,"position":18,"created_at":"2024-04-09T16:56:45-07:00","updated_at":"2024-04-09T16:57:56-07:00","alt":null,"width":1080,"height":1080,"src":"https:\/\/cdn.shopify.com\/s\/files\/1\/0605\/8790\/1127\/files\/6.png?v=1712707076","variant_ids":[]},{"id":39195773698247,"product_id":7940456054983,"position":19,"created_at":"2024-04-09T16:56:45-07:00","updated_at":"2024-04-09T16:57:56-07:00","alt":null,"width":2172,"height":2172,"src":"https:\/\/cdn.shopify.com\/s\/files\/1\/0605\/8790\/1127\/files\/IMG_1456.heic?v=1712707076","variant_ids":[]},{"id":39195774091463,"product_id":7940456054983,"position":20,"created_at":"2024-04-09T16:56:45-07:00","updated_at":"2024-04-09T16:57:56-07:00","alt":null,"width":2103,"height":2103,"src":"https:\/\/cdn.shopify.com\/s\/files\/1\/0605\/8790\/1127\/files\/IMG_1457.heic?v=1712707076","variant_ids":[]},{"id":39195773173959,"product_id":7940456054983,"position":21,"created_at":"2024-04-09T16:56:45-07:00","updated_at":"2024-04-09T16:57:56-07:00","alt":null,"width":2007,"height":2007,"src":"https:\/\/cdn.shopify.com\/s\/files\/1\/0605\/8790\/1127\/files\/IMG_1459.heic?v=1712707076","variant_ids":[]},{"id":39195773894855,"product_id":7940456054983,"position":22,"created_at":"2024-04-09T16:56:45-07:00","updated_at":"2024-04-09T16:57:56-07:00","alt":null,"width":1904,"height":1904,"src":"https:\/\/cdn.shopify.com\/s\/files\/1\/0605\/8790\/1127\/files\/IMG_1460.heic?v=1712707076","variant_ids":[]},{"id":39195773206727,"product_id":7940456054983,"position":23,"created_at":"2024-04-09T16:56:45-07:00","updated_at":"2024-04-09T16:57:56-07:00","alt":null,"width":1904,"height":1904,"src":"https:\/\/cdn.shopify.com\/s\/files\/1\/0605\/8790\/1127\/files\/IMG_1461.heic?v=1712707076","variant_ids":[]},{"id":39195773731015,"product_id":7940456054983,"position":24,"created_at":"2024-04-09T16:56:45-07:00","updated_at":"2024-04-09T16:57:56-07:00","alt":null,"width":1915,"height":1915,"src":"https:\/\/cdn.shopify.com\/s\/files\/1\/0605\/8790\/1127\/files\/IMG_1462.heic?v=1712707076","variant_ids":[]},{"id":39195774288071,"product_id":7940456054983,"position":25,"created_at":"2024-04-09T16:56:45-07:00","updated_at":"2024-04-09T16:57:56-07:00","alt":null,"width":2003,"height":2003,"src":"https:\/\/cdn.shopify.com\/s\/files\/1\/0605\/8790\/1127\/files\/IMG_1463.heic?v=1712707076","variant_ids":[]},{"id":39195774124231,"product_id":7940456054983,"position":26,"created_at":"2024-04-09T16:56:45-07:00","updated_at":"2024-04-09T16:57:56-07:00","alt":null,"width":2310,"height":2310,"src":"https:\/\/cdn.shopify.com\/s\/files\/1\/0605\/8790\/1127\/files\/IMG_1481.heic?v=1712707076","variant_ids":[]}],"image":{"id":39195774320839,"product_id":7940456054983,"position":1,"created_at":"2024-04-09T16:56:45-07:00","updated_at":"2024-04-09T16:57:56-07:00","alt":null,"width":2657,"height":2657,"src":"https:\/\/cdn.shopify.com\/s\/files\/1\/0605\/8790\/1127\/files\/IMG_1474.heic?v=1712707076","variant_ids":[]}}}